cryptopycode/__init__.py
cryptopycode/cryptopycode.py
cryptopycode-0.0.dist-info/LICENSE
cryptopycode-0.0.dist-info/METADATA
cryptopycode-0.0.dist-info/WHEEL
cryptopycode-0.0.dist-info/top_level.txt
cryptopycode-0.0.dist-info/RECORD
